odoo8_addon_l10n_ar_wsaa-8.0.1.0.0.99.dev3-nspkg.pth
odoo_addons/l10n_ar_wsaa/.gitignore
odoo_addons/l10n_ar_wsaa/__init__.py
odoo_addons/l10n_ar_wsaa/__openerp__.py
odoo_addons/l10n_ar_wsaa/wsaa.py
odoo_addons/l10n_ar_wsaa/wsaa_demo.xml
odoo_addons/l10n_ar_wsaa/wsaa_suds.py
odoo_addons/l10n_ar_wsaa/wsaa_view.xml
odoo_addons/l10n_ar_wsaa/security/ir.model.access.csv
odoo_addons/l10n_ar_wsaa/static/description/icon.png
odoo_addons/l10n_ar_wsaa/tests/__init__.py
odoo_addons/l10n_ar_wsaa/tests/common.py
odoo_addons/l10n_ar_wsaa/tests/test_wsaa.py
odoo_addons/l10n_ar_wsaa/wizard/__init__.py
odoo_addons/l10n_ar_wsaa/wizard/wsaa_load_config.py
odoo_addons/l10n_ar_wsaa/wizard/wsaa_load_config_view.xml
odoo8_addon_l10n_ar_wsaa-8.0.1.0.0.99.dev3.dist-info/METADATA
odoo8_addon_l10n_ar_wsaa-8.0.1.0.0.99.dev3.dist-info/WHEEL
odoo8_addon_l10n_ar_wsaa-8.0.1.0.0.99.dev3.dist-info/namespace_packages.txt
odoo8_addon_l10n_ar_wsaa-8.0.1.0.0.99.dev3.dist-info/top_level.txt
odoo8_addon_l10n_ar_wsaa-8.0.1.0.0.99.dev3.dist-info/RECORD
