Metadata-Version: 2.1
Name: odoo8-addon-l10n-ar-wsaa
Version: 8.0.1.0.0.99.dev3
Summary: WSAA
Home-page: http://proyectoaconcagua.com.ar
Author: Proyecto Aconcagua
License: GPL-3
Platform: UNKNOWN
Classifier: Programming Language :: Python
Classifier: Framework :: Odoo
Classifier: License :: OSI Approved :: GNU General Public License v3 (GPLv3)
Requires-Python: ~=2.7
Requires-Dist: odoo (<9.0a,>=8.0a)
